tlfs/__about__.py
tlfs/__init__.py
tlfs/scripts.py
tlfs/tlf.py
tlfs-0.0.5.dist-info/METADATA
tlfs-0.0.5.dist-info/WHEEL
tlfs-0.0.5.dist-info/entry_points.txt
tlfs-0.0.5.dist-info/licenses/LICENSE.txt
tlfs-0.0.5.dist-info/RECORD
