Metadata-Version: 2.3
Name: tlfs
Version: 0.0.5
Summary: Classes and scripts to create TLFs (Table, Listing, Figures shells) quickly and in an opinionated way.
Project-URL: Documentation, https://github.com/lbraglia/tlfs#readme
Project-URL: Issues, https://github.com/lbraglia/tlfs/issues
Project-URL: Source, https://github.com/lbraglia/tlfs
Author-email: Luca Braglia <lbraglia@gmail.com>
License-Expression: MIT
License-File: LICENSE.txt
Classifier: Development Status :: 4 - Beta
Classifier: Programming Language :: Python
Classifier: Programming Language :: Python :: 3.8
Classifier: Programming Language :: Python :: 3.9
Classifier: Programming Language :: Python :: 3.10
Classifier: Programming Language :: Python :: 3.11
Classifier: Programming Language :: Python :: 3.12
Classifier: Programming Language :: Python :: Implementation :: CPython
Classifier: Programming Language :: Python :: Implementation :: PyPy
Requires-Python: >=3.8
Requires-Dist: docx
Requires-Dist: multimethod
Requires-Dist: numpy
Requires-Dist: pandas
